{
  "0.1 Data försäljning": {
    "2026-02-02": {
      "Kund": "Telia",
      "Projekt": "Telia VIP Leads",
      "Datum": "2026-02-02",
      "År-månad": "2026-02",
      "Kundnummer": "",
      "Personnummer": "199108224479",
      "Namn": "Ali Al-Dhahir",
      "Telefonnummer": "0736888624",
      "Epostadress": "ali1991al@hotmail.com",
      "Gatuadress": "Sturegatan 39B",
      "Postnummer": "79151",
      "Ort": "Falun",
      "Produkt": "BB250",
      "Produkttyp": "Produkt",
      "Produktkod": "BB250",
      "Säljare": "Adel Hamed Ahmed",
      "LoxysoftID": 14194,
      "Team": "",
      "Prospekt ID": 65403743,
      "nyckel": "Telia VIP LeadsBB250Produkt",
      "kolumn?": "Bredband",
      "Provition kontroll": 1,
      "FINNS TID": 1,
      "provision trappa": 42
    },
    "2026-02-01": {
      "Kund": "Telia",
      "Projekt": "Telia D2D",
      "Datum": "2026-02-01",
      "År-månad": "2026-02",
      "Kundnummer": 55819150,
      "Personnummer": "198208042013",
      "Namn": "Marcus Andersson",
      "Telefonnummer": 0,
      "Gatuadress": "MUNKBROGATAN 17",
      "Postnummer": "61434",
      "Ort": "SÖDERKÖPING",
      "Produkt": "TV Mellan",
      "Produkttyp": "Produkt",
      "Produktkod": "TV Mellan",
      "Säljare": "Javed Beg",
      "LoxysoftID": 5705,
      "nyckel": "Telia D2DTV MellanProdukt",
      "kolumn?": "TV",
      "Provition kontroll": 1,
      "FINNS TID": 1,
      "provision trappa": 0
    },
    "2026-02-03": {
      "Kund": "Telia",
      "Projekt": "Telia VIP Leads",
      "Datum": "2026-02-03",
      "År-månad": "2026-02",
      "Kundnummer": "",
      "Personnummer": "195405198556",
      "Namn": "Thomas Engberg",
      "Telefonnummer": "0703761312",
      "Epostadress": "Thomas_engberg@hotmail.com",
      "Gatuadress": "HEMVÄGEN 9",
      "Postnummer": "90336",
      "Ort": "Umeå",
      "Produkt": "Streaming mer",
      "Produkttyp": "Tilläggsprodukt",
      "Produktkod": "Streaming mer",
      "Säljare": "Noah Bhattarai",
      "LoxysoftID": 15026,
      "Team": "",
      "Prospekt ID": 65405578,
      "nyckel": "Telia VIP LeadsStreaming merTilläggsprodukt",
      "kolumn?": "Film",
      "Provition kontroll": 1,
      "FINNS TID": 1,
      "provision trappa": 42
    },
    "2026-02-04": {
      "Kund": "Telia",
      "Projekt": "Telia VIP Leads",
      "Datum": "2026-02-04",
      "År-månad": "2026-02",
      "Kundnummer": "",
      "Personnummer": "196201283352",
      "Namn": "Jesper Kalling",
      "Telefonnummer": "0721631583",
      "Epostadress": "kallings@hotmail.com",
      "Gatuadress": "Kommendervägen 6",
      "Postnummer": "24751",
      "Ort": "Dalby",
      "Produkt": "BB300",
      "Produkttyp": "Produkt",
      "Produktkod": "BB300",
      "Säljare": "Lloyd Antwi",
      "LoxysoftID": 14866,
      "Team": "",
      "Prospekt ID": 65408685,
      "nyckel": "Telia VIP LeadsBB300Produkt",
      "kolumn?": "Bredband",
      "Provition kontroll": 1,
      "FINNS TID": 1,
      "provision trappa": 42
    },
    "2026-02-05": {
      "Kund": "Telia",
      "Projekt": "Telia VIP Leads",
      "Datum": "2026-02-05",
      "År-månad": "2026-02",
      "Kundnummer": "",
      "Personnummer": "195805177184",
      "Namn": "Charlotte Caster",
      "Telefonnummer": "0729200456",
      "Epostadress": "cbcvxo@gmail.com",
      "Gatuadress": "Pilgatan 4",
      "Postnummer": "35236",
      "Ort": "Växjö",
      "Produkt": "BB100",
      "Produkttyp": "Produkt",
      "Produktkod": "BB100",
      "Säljare": "Adel Hamed Ahmed",
      "LoxysoftID": 14194,
      "Team": "",
      "Prospekt ID": 65411809,
      "nyckel": "Telia VIP LeadsBB100Produkt",
      "kolumn?": "Bredband",
      "Provition kontroll": 1,
      "FINNS TID": 1,
      "provision trappa": 42
    },
    "2026-02-07": {
      "Kund": "Telia",
      "Projekt": "Telia D2D",
      "Datum": "2026-02-07",
      "År-månad": "2026-02",
      "Kundnummer": 55901858,
      "Personnummer": "197310302836",
      "Namn": "Per Hildingsson",
      "Telefonnummer": 0,
      "Gatuadress": "GÄRDESVÄGEN 8",
      "Postnummer": "34250",
      "Ort": "VISLANDA",
      "Produkt": "TV4 Play Sport Total",
      "Produkttyp": "Produkt",
      "Produktkod": "TV4 Play Sport Total",
      "Säljare": "Sebastian Polles",
      "LoxysoftID": 6549,
      "nyckel": "Telia D2DTV4 Play Sport TotalProdukt",
      "kolumn?": "Streaming",
      "Provition kontroll": 1,
      "FINNS TID": 1,
      "provision trappa": 0
    },
    "2026-02-06": {
      "Kund": "Telia",
      "Projekt": "Telia VIP Leads",
      "Datum": "2026-02-06",
      "År-månad": "2026-02",
      "Kundnummer": "",
      "Personnummer": "197012070137",
      "Namn": "Thomas s Wessberg",
      "Telefonnummer": "0708658108",
      "Epostadress": "twessberg7@gmail.com",
      "Gatuadress": "Liljevägen 3,19460 Upplands Väsby",
      "Postnummer": "",
      "Ort": "",
      "Produkt": "TV Box",
      "Produkttyp": "Tilläggsprodukt",
      "Produktkod": "TV Box",
      "Säljare": "Marcel Kocon",
      "LoxysoftID": 14920,
      "Team": "",
      "Prospekt ID": 65422488,
      "nyckel": "Telia VIP LeadsTV BoxTilläggsprodukt",
      "kolumn?": "TV BOX",
      "Provition kontroll": 1,
      "FINNS TID": 1,
      "provision trappa": 42
    },
    "2026-02-08": {
      "Kund": "Telia",
      "Projekt": "Telia D2D",
      "Datum": "2026-02-08",
      "År-månad": "2026-02",
      "Kundnummer": 55915650,
      "Personnummer": "195502102709",
      "Namn": "Ann Johansson",
      "Telefonnummer": 0,
      "Gatuadress": "ÄLGVÄGEN 1",
      "Postnummer": "36231",
      "Ort": "TINGSRYD",
      "Produkt": "Extra användare",
      "Produkttyp": "Produkt",
      "Produktkod": "Extra användare",
      "Säljare": "Samir Nduwayo",
      "LoxysoftID": 6135,
      "nyckel": "Telia D2DExtra användareProdukt",
      "kolumn?": "Mobil",
      "Provition kontroll": 1,
      "FINNS TID": 1,
      "provision trappa": 0
    },
    "2026-02-09": {
      "Kund": "Telia",
      "Projekt": "Telia VIP Leads",
      "Datum": "2026-02-09",
      "År-månad": "2026-02",
      "Kundnummer": "",
      "Personnummer": "195909121450",
      "Namn": "Anders Jespersson",
      "Telefonnummer": "0707271283",
      "Epostadress": "anders.jespersson@soderbergpartners.se",
      "Gatuadress": "Husby-Sjutolfts-Nibble 2,74950 Ekolsund",
      "Postnummer": "",
      "Ort": "",
      "Produkt": "TV Box",
      "Produkttyp": "Tilläggsprodukt",
      "Produktkod": "TV Box",
      "Säljare": "Marcel Kocon",
      "LoxysoftID": 14920,
      "Team": "",
      "Prospekt ID": 65431223,
      "nyckel": "Telia VIP LeadsTV BoxTilläggsprodukt",
      "kolumn?": "TV BOX",
      "Provition kontroll": 1,
      "FINNS TID": 1,
      "provision trappa": 42
    },
    "2026-02-10": {
      "Kund": "Telia",
      "Projekt": "Telia VIP Leads",
      "Datum": "2026-02-10",
      "År-månad": "2026-02",
      "Kundnummer": "",
      "Personnummer": "197910026645",
      "Namn": "Tove Carlsson",
      "Telefonnummer": "0703707454",
      "Epostadress": "tovesbrev@hotmail.com",
      "Gatuadress": "Hindergårdsgatan 16B",
      "Postnummer": "70381",
      "Ort": "Örebro",
      "Produkt": "Streaming mer",
      "Produkttyp": "Tilläggsprodukt",
      "Produktkod": "Streaming mer",
      "Säljare": "Adel Hamed Ahmed",
      "LoxysoftID": 14194,
      "Team": "",
      "Prospekt ID": 65448233,
      "nyckel": "Telia VIP LeadsStreaming merTilläggsprodukt",
      "kolumn?": "Film",
      "Provition kontroll": 1,
      "FINNS TID": 1,
      "provision trappa": 42
    },
    "2026-02-11": {
      "Kund": "Telia",
      "Projekt": "Telia VIP Leads",
      "Datum": "2026-02-11",
      "År-månad": "2026-02",
      "Kundnummer": "",
      "Personnummer": "194705294835",
      "Namn": "Anders Janson",
      "Telefonnummer": "0723023592",
      "Epostadress": "fire.janson1@gmail.com",
      "Gatuadress": "Hallandsås Börkered 309",
      "Postnummer": "31297",
      "Ort": "Laholm",
      "Produkt": "BB100",
      "Produkttyp": "Produkt",
      "Produktkod": "BB100",
      "Säljare": "Noah Bhattarai",
      "LoxysoftID": 15026,
      "Team": "",
      "Prospekt ID": 65451002,
      "nyckel": "Telia VIP LeadsBB100Produkt",
      "kolumn?": "Bredband",
      "Provition kontroll": 1,
      "FINNS TID": 1,
      "provision trappa": 42
    },
    "2026-02-12": {
      "Kund": "Telia",
      "Projekt": "Telia VIP Leads",
      "Datum": "2026-02-12",
      "År-månad": "2026-02",
      "Kundnummer": "",
      "Personnummer": "198009234082",
      "Namn": "Jessica Hagberg",
      "Telefonnummer": "0704807038",
      "Epostadress": "jessica.hagberg@icloud.com",
      "Gatuadress": "Tyringegatan 88",
      "Postnummer": "25276",
      "Ort": "Helsingborg",
      "Produkt": "Mobil Obegränsad Plus",
      "Produkttyp": "Tilläggsprodukt",
      "Produktkod": "Mobil Obegränsad Plus",
      "Säljare": "Mobin Said",
      "LoxysoftID": 15091,
      "Team": "",
      "Prospekt ID": 65455117,
      "nyckel": "Telia VIP LeadsMobil Obegränsad PlusTilläggsprodukt",
      "kolumn?": "Mobil",
      "Provition kontroll": 1,
      "FINNS TID": 1,
      "provision trappa": 42
    },
    "2026-02-13": {
      "Kund": "Telia",
      "Projekt": "Telia VIP Leads",
      "Datum": "2026-02-13",
      "År-månad": "2026-02",
      "Kundnummer": "",
      "Personnummer": "197211232405",
      "Namn": "Annelie Johansson",
      "Telefonnummer": "0702620422",
      "Epostadress": "anneliesimba@hotmail.com",
      "Gatuadress": "Klostergatan lgh 1201 27",
      "Postnummer": "55335",
      "Ort": "Jönköping",
      "Produkt": "TV Mini",
      "Produkttyp": "Tilläggsprodukt",
      "Produktkod": "TV Mini",
      "Säljare": "Oscar Thalin",
      "LoxysoftID": 14372,
      "Team": "",
      "Prospekt ID": 65463530,
      "nyckel": "Telia VIP LeadsTV MiniTilläggsprodukt",
      "kolumn?": "TV",
      "Provition kontroll": 1,
      "FINNS TID": 1,
      "provision trappa": 42
    },
    "2026-02-14": {
      "Kund": "Telia",
      "Projekt": "Telia D2D",
      "Datum": "2026-02-14",
      "År-månad": "2026-02",
      "Kundnummer": 56026981,
      "Personnummer": "197103060013",
      "Namn": "Mikael Jansson",
      "Telefonnummer": 0,
      "Gatuadress": "UTHAMRAVÄGEN 11",
      "Postnummer": "18653",
      "Ort": "VALLENTUNA",
      "Produkt": "All film & serier från Netflix, TV4 Play, Amazon Prime & HBO Max",
      "Produkttyp": "Produkt",
      "Produktkod": "All film & serier från Netflix, TV4 Play, Amazon Prime & HBO Max",
      "Säljare": "Ali Fakih",
      "LoxysoftID": 5833,
      "nyckel": "Telia D2DAll film & serier från Netflix, TV4 Play, Amazon Prime & HBO MaxProdukt",
      "kolumn?": "Streaming",
      "Provition kontroll": 1,
      "FINNS TID": 1,
      "provision trappa": 0
    },
    "2026-02-15": {
      "Kund": "Telia",
      "Projekt": "Telia D2D",
      "Datum": "2026-02-15",
      "År-månad": "2026-02",
      "Kundnummer": 56024069,
      "Personnummer": "199907306220",
      "Namn": "Frida Sundqvist",
      "Telefonnummer": 0,
      "Gatuadress": "BÄLLSTAVÄGEN 40",
      "Postnummer": "86432",
      "Ort": "MATFORS",
      "Produkt": "TV Mini",
      "Produkttyp": "Produkt",
      "Produktkod": "TV Mini",
      "Säljare": "Max Nordenvärn",
      "LoxysoftID": 6264,
      "nyckel": "Telia D2DTV MiniProdukt",
      "kolumn?": "TV",
      "Provition kontroll": 1,
      "FINNS TID": 1,
      "provision trappa": 0
    },
    "2026-02-16": {
      "Kund": "Telia",
      "Projekt": "Telia VIP Leads",
      "Datum": "2026-02-16",
      "År-månad": "2026-02",
      "Kundnummer": "",
      "Personnummer": "194306210701",
      "Namn": "Inger Eriksson",
      "Telefonnummer": "0722299290",
      "Epostadress": "ingereriksson1@outlook.com",
      "Gatuadress": "Vindragarvägen 16",
      "Postnummer": "11750",
      "Ort": "Stockholm",
      "Produkt": "Mobil Obegränsad Plus",
      "Produkttyp": "Tilläggsprodukt",
      "Produktkod": "Mobil Obegränsad Plus",
      "Säljare": "Noah Bhattarai",
      "LoxysoftID": 15026,
      "Team": "",
      "Prospekt ID": 65469429,
      "nyckel": "Telia VIP LeadsMobil Obegränsad PlusTilläggsprodukt",
      "kolumn?": "Mobil",
      "Provition kontroll": 1,
      "FINNS TID": 1,
      "provision trappa": 42
    },
    "2026-02-17": {
      "Kund": "Telia",
      "Projekt": "Telia VIP Leads",
      "Datum": "2026-02-17",
      "År-månad": "2026-02",
      "Kundnummer": "",
      "Personnummer": "196901023330",
      "Namn": "magnus Danielsson",
      "Telefonnummer": "0793360934",
      "Epostadress": "mangenr155@gmail.com",
      "Gatuadress": "villavägen  25",
      "Postnummer": "37373",
      "Ort": "Karlskrona",
      "Produkt": "BB100",
      "Produkttyp": "Produkt",
      "Produktkod": "BB100",
      "Säljare": "Marcel Kocon",
      "LoxysoftID": 14920,
      "Team": "",
      "Prospekt ID": 65478709,
      "nyckel": "Telia VIP LeadsBB100Produkt",
      "kolumn?": "Bredband",
      "Provition kontroll": 1,
      "FINNS TID": 1,
      "provision trappa": 42
    },
    "2026-02-18": {
      "Kund": "Telia",
      "Projekt": "Telia VIP Leads",
      "Datum": "2026-02-18",
      "År-månad": "2026-02",
      "Kundnummer": "",
      "Personnummer": "196502203109",
      "Namn": "Veronica Andersson",
      "Telefonnummer": "0706606283",
      "Epostadress": "vemo65@yahoo.se",
      "Gatuadress": "Ättestigen 4",
      "Postnummer": "41674",
      "Ort": "Göteborg",
      "Produkt": "Mobil Obegränsad Plus",
      "Produkttyp": "Tilläggsprodukt",
      "Produktkod": "Mobil Obegränsad Plus",
      "Säljare": "Adel Hamed Ahmed",
      "LoxysoftID": 14194,
      "Team": "",
      "Prospekt ID": 65487493,
      "nyckel": "Telia VIP LeadsMobil Obegränsad PlusTilläggsprodukt",
      "kolumn?": "Mobil",
      "Provition kontroll": 1,
      "FINNS TID": 1,
      "provision trappa": 42
    },
    "2026-02-19": {
      "Kund": "Telia",
      "Projekt": "Telia VIP Leads",
      "Datum": "2026-02-19",
      "År-månad": "2026-02",
      "Kundnummer": "",
      "Personnummer": "197911293954",
      "Namn": "Danny Regnér",
      "Telefonnummer": "0706144338",
      "Epostadress": "Sverige470@hotmail.com",
      "Gatuadress": "Västeråkers-Berga 15",
      "Postnummer": "75591",
      "Ort": "Uppsala",
      "Produkt": "Streaming mer",
      "Produkttyp": "Tilläggsprodukt",
      "Produktkod": "Streaming mer",
      "Säljare": "Noah Bhattarai",
      "LoxysoftID": 15026,
      "Team": "",
      "Prospekt ID": 65489553,
      "nyckel": "Telia VIP LeadsStreaming merTilläggsprodukt",
      "kolumn?": "Film",
      "Provition kontroll": 1,
      "FINNS TID": 1,
      "provision trappa": 42
    },
    "2026-02-20": {
      "Kund": "Telia",
      "Projekt": "Telia VIP Leads",
      "Datum": "2026-02-20",
      "År-månad": "2026-02",
      "Kundnummer": "",
      "Personnummer": "197202120171",
      "Namn": "Peter Malmström",
      "Telefonnummer": "0730701796",
      "Epostadress": "Peter@masicapital.se",
      "Gatuadress": "Granbacksvägen 3",
      "Postnummer": "18233",
      "Ort": "Danderyd",
      "Produkt": "BB1000",
      "Produkttyp": "Produkt",
      "Produktkod": "BB1000",
      "Säljare": "Noah Bhattarai",
      "LoxysoftID": 15026,
      "Team": "",
      "Prospekt ID": 65494895,
      "nyckel": "Telia VIP LeadsBB1000Produkt",
      "kolumn?": "Bredband",
      "Provition kontroll": 1,
      "FINNS TID": 1,
      "provision trappa": 42
    },
    "2026-02-21": {
      "Kund": "Telia",
      "Projekt": "Telia D2D",
      "Datum": "2026-02-21",
      "År-månad": "2026-02",
      "Kundnummer": 56114101,
      "Personnummer": "197510166932",
      "Namn": "Ted Nilsson",
      "Telefonnummer": 0,
      "Gatuadress": "LANDSLAGSGATAN 35",
      "Postnummer": "72475",
      "Ort": "VÄSTERÅS",
      "Produkt": "TV Mini",
      "Produkttyp": "Produkt",
      "Produktkod": "TV Mini",
      "Säljare": "Ali Fakih",
      "LoxysoftID": 5833,
      "nyckel": "Telia D2DTV MiniProdukt",
      "kolumn?": "TV",
      "Provition kontroll": 1,
      "FINNS TID": 1,
      "provision trappa": 0
    },
    "2026-02-22": {
      "Kund": "Telia",
      "Projekt": "Telia D2D",
      "Datum": "2026-02-22",
      "År-månad": "2026-02",
      "Kundnummer": 56123087,
      "Personnummer": "199005094918",
      "Namn": "Patric Bjurman",
      "Telefonnummer": 0,
      "Gatuadress": "ASKÖ 6",
      "Postnummer": "72591",
      "Ort": "VÄSTERÅS",
      "Produkt": "10GB",
      "Produkttyp": "Produkt",
      "Produktkod": "10GB",
      "Säljare": "Ali Fakih",
      "LoxysoftID": 5833,
      "nyckel": "Telia D2D10GBProdukt",
      "kolumn?": "Mobil",
      "Provition kontroll": 1,
      "FINNS TID": 1,
      "provision trappa": 0
    },
    "2026-02-23": {
      "Kund": "Tele2",
      "Projekt": "Tele2 Villafiber",
      "Datum": "2026-02-23",
      "År-månad": "2026-02",
      "Kundnummer": 6132203,
      "Personnummer": "198011209072",
      "Gatuadress": "KORTA VÄGEN 1",
      "Postnummer": 13549,
      "Ort": "TYRESÖ",
      "Produkt": "Bredband Nyteckning LAN",
      "Produkttyp": "Produkt",
      "Produktkod": "Bredband Nyteckning LAN",
      "Säljare": "August Fabian",
      "LoxysoftID": 6393,
      "nyckel": "Tele2 VillafiberBredband Nyteckning LANProdukt",
      "kolumn?": "Bredband",
      "Provition kontroll": 1,
      "FINNS TID": 1,
      "provision trappa": 162
    }
  },
  "0.0 Data Timmar": {
    "2026-02-02": {
      "Kund": "Global Connect",
      "Projekt": "Global Connect TM Jan",
      "Säljare": "Victor Shahnazi",
      "Loxysoft ID": 4922,
      "Datum": "2026-02-02",
      "År-månad": "2026-02",
      "Overksam tid": "0:00:00",
      "Overksam tid timmar": 0,
      "Väntetid": "0:00:00",
      "Väntetid timmar": 0,
      "Hanteringstid timmar": 0,
      "Inloggad tid": "8:00:00",
      "Inloggad tid timmar": 8,
      "Samtalstid": "0:00:00",
      "Samtalstid timmar": 0,
      "Efterbearbetstid": "0:00:00",
      "Efterbearbetstid timmar": 0,
      "Genomsnittlig samtalstid": "0:00:00",
      "Genomsnittlig samtalstid timmar": 0,
      "Genomsnittlig samtalstid/Order": "0:00:00",
      "Genomsnittlig samtalstid/Order timmar": 0,
      "Registrerade samtal": 0,
      "Registrerade prospekt": 0,
      "Avbrutit samtalsbegäran": 0,
      "Mansdagar": 1
    },
    "2026-02-01": {
      "Kund": "Telia",
      "Projekt": "Telia D2D",
      "Säljare": "Javed Beg",
      "Loxysoft ID": 5705,
      "Datum": "2026-02-01",
      "År-månad": "2026-02",
      "Overksam tid": "0:00:00",
      "Overksam tid timmar": 0,
      "Väntetid": "0:00:00",
      "Väntetid timmar": 0,
      "Hanteringstid timmar": 0,
      "Inloggad tid": "1:00:00",
      "Inloggad tid timmar": 1,
      "Samtalstid": "0:00:00",
      "Samtalstid timmar": 0,
      "Efterbearbetstid": "0:00:00",
      "Efterbearbetstid timmar": 0,
      "Genomsnittlig samtalstid": "0:00:00",
      "Genomsnittlig samtalstid timmar": 0,
      "Genomsnittlig samtalstid/Order": "0:00:00",
      "Genomsnittlig samtalstid/Order timmar": 0,
      "Registrerade samtal": 0,
      "Registrerade prospekt": 0,
      "Avbrutit samtalsbegäran": 0
    },
    "2026-02-03": {
      "Kund": "Global Connect",
      "Projekt": "Global Connect TM Jan",
      "Säljare": "Victor Shahnazi",
      "Loxysoft ID": 4922,
      "Datum": "2026-02-03",
      "År-månad": "2026-02",
      "Overksam tid": "0:00:00",
      "Overksam tid timmar": 0,
      "Väntetid": "0:00:00",
      "Väntetid timmar": 0,
      "Hanteringstid timmar": 0,
      "Inloggad tid": "8:00:00",
      "Inloggad tid timmar": 8,
      "Samtalstid": "0:00:00",
      "Samtalstid timmar": 0,
      "Efterbearbetstid": "0:00:00",
      "Efterbearbetstid timmar": 0,
      "Genomsnittlig samtalstid": "0:00:00",
      "Genomsnittlig samtalstid timmar": 0,
      "Genomsnittlig samtalstid/Order": "0:00:00",
      "Genomsnittlig samtalstid/Order timmar": 0,
      "Registrerade samtal": 0,
      "Registrerade prospekt": 0,
      "Avbrutit samtalsbegäran": 0,
      "Mansdagar": 1
    },
    "2026-02-04": {
      "Kund": "Global Connect",
      "Projekt": "Global Connect TM Jan",
      "Säljare": "Victor Shahnazi",
      "Loxysoft ID": 4922,
      "Datum": "2026-02-04",
      "År-månad": "2026-02",
      "Overksam tid": "0:00:00",
      "Overksam tid timmar": 0,
      "Väntetid": "0:00:00",
      "Väntetid timmar": 0,
      "Hanteringstid timmar": 0,
      "Inloggad tid": "8:00:00",
      "Inloggad tid timmar": 8,
      "Samtalstid": "0:00:00",
      "Samtalstid timmar": 0,
      "Efterbearbetstid": "0:00:00",
      "Efterbearbetstid timmar": 0,
      "Genomsnittlig samtalstid": "0:00:00",
      "Genomsnittlig samtalstid timmar": 0,
      "Genomsnittlig samtalstid/Order": "0:00:00",
      "Genomsnittlig samtalstid/Order timmar": 0,
      "Registrerade samtal": 0,
      "Registrerade prospekt": 0,
      "Avbrutit samtalsbegäran": 0,
      "Mansdagar": 1
    },
    "2026-02-05": {
      "Kund": "Global Connect",
      "Projekt": "Global Connect TM Jan",
      "Säljare": "Victor Shahnazi",
      "Loxysoft ID": 4922,
      "Datum": "2026-02-05",
      "År-månad": "2026-02",
      "Overksam tid": "0:00:00",
      "Overksam tid timmar": 0,
      "Väntetid": "0:00:00",
      "Väntetid timmar": 0,
      "Hanteringstid timmar": 0,
      "Inloggad tid": "8:00:00",
      "Inloggad tid timmar": 8,
      "Samtalstid": "0:00:00",
      "Samtalstid timmar": 0,
      "Efterbearbetstid": "0:00:00",
      "Efterbearbetstid timmar": 0,
      "Genomsnittlig samtalstid": "0:00:00",
      "Genomsnittlig samtalstid timmar": 0,
      "Genomsnittlig samtalstid/Order": "0:00:00",
      "Genomsnittlig samtalstid/Order timmar": 0,
      "Registrerade samtal": 0,
      "Registrerade prospekt": 0,
      "Avbrutit samtalsbegäran": 0,
      "Mansdagar": 1
    },
    "2026-02-06": {
      "Kund": "Tele2",
      "Projekt": "Tele2 Villafiber",
      "Säljare": "Kristian Crnoja",
      "Loxysoft ID": 6618,
      "Datum": "2026-02-06",
      "År-månad": "2026-02",
      "Overksam tid": "0:00:00",
      "Overksam tid timmar": 0,
      "Väntetid": "0:00:00",
      "Väntetid timmar": 0,
      "Hanteringstid timmar": 0,
      "Inloggad tid": "9:00:00",
      "Inloggad tid timmar": 1,
      "Samtalstid": "0:00:00",
      "Samtalstid timmar": 0,
      "Efterbearbetstid": "0:00:00",
      "Efterbearbetstid timmar": 0,
      "Genomsnittlig samtalstid": "0:00:00",
      "Genomsnittlig samtalstid timmar": 0,
      "Genomsnittlig samtalstid/Order": "0:00:00",
      "Genomsnittlig samtalstid/Order timmar": 0,
      "Registrerade samtal": 0,
      "Registrerade prospekt": 0,
      "Avbrutit samtalsbegäran": 0
    },
    "2026-02-07": {
      "Kund": "Telia",
      "Projekt": "Telia D2D",
      "Säljare": "Sebastian Polles",
      "Loxysoft ID": 6549,
      "Datum": "2026-02-07",
      "År-månad": "2026-02",
      "Overksam tid": "0:00:00",
      "Overksam tid timmar": 0,
      "Väntetid": "0:00:00",
      "Väntetid timmar": 0,
      "Hanteringstid timmar": 0,
      "Inloggad tid": "1:00:00",
      "Inloggad tid timmar": 1,
      "Samtalstid": "0:00:00",
      "Samtalstid timmar": 0,
      "Efterbearbetstid": "0:00:00",
      "Efterbearbetstid timmar": 0,
      "Genomsnittlig samtalstid": "0:00:00",
      "Genomsnittlig samtalstid timmar": 0,
      "Genomsnittlig samtalstid/Order": "0:00:00",
      "Genomsnittlig samtalstid/Order timmar": 0,
      "Registrerade samtal": 0,
      "Registrerade prospekt": 0,
      "Avbrutit samtalsbegäran": 0
    },
    "2026-02-08": {
      "Kund": "Telia",
      "Projekt": "Telia D2D",
      "Säljare": "Samir Nduwayo",
      "Loxysoft ID": 6135,
      "Datum": "2026-02-08",
      "År-månad": "2026-02",
      "Overksam tid": "0:00:00",
      "Overksam tid timmar": 0,
      "Väntetid": "0:00:00",
      "Väntetid timmar": 0,
      "Hanteringstid timmar": 0,
      "Inloggad tid": "1:00:00",
      "Inloggad tid timmar": 1,
      "Samtalstid": "0:00:00",
      "Samtalstid timmar": 0,
      "Efterbearbetstid": "0:00:00",
      "Efterbearbetstid timmar": 0,
      "Genomsnittlig samtalstid": "0:00:00",
      "Genomsnittlig samtalstid timmar": 0,
      "Genomsnittlig samtalstid/Order": "0:00:00",
      "Genomsnittlig samtalstid/Order timmar": 0,
      "Registrerade samtal": 0,
      "Registrerade prospekt": 0,
      "Avbrutit samtalsbegäran": 0
    },
    "2026-02-09": {
      "Kund": "Global Connect",
      "Projekt": "Global Connect TM Jan",
      "Säljare": "Sole Petrovic",
      "Loxysoft ID": 6398,
      "Datum": "2026-02-09",
      "År-månad": "2026-02",
      "Overksam tid": "0:00:00",
      "Overksam tid timmar": 0,
      "Väntetid": "0:00:00",
      "Väntetid timmar": 0,
      "Hanteringstid timmar": 0,
      "Inloggad tid": "8:00:00",
      "Inloggad tid timmar": 8,
      "Samtalstid": "0:00:00",
      "Samtalstid timmar": 0,
      "Efterbearbetstid": "0:00:00",
      "Efterbearbetstid timmar": 0,
      "Genomsnittlig samtalstid": "0:00:00",
      "Genomsnittlig samtalstid timmar": 0,
      "Genomsnittlig samtalstid/Order": "0:00:00",
      "Genomsnittlig samtalstid/Order timmar": 0,
      "Registrerade samtal": 0,
      "Registrerade prospekt": 0,
      "Avbrutit samtalsbegäran": 0,
      "Mansdagar": 1
    },
    "2026-02-10": {
      "Kund": "Global Connect",
      "Projekt": "Global Connect TM Jan",
      "Säljare": "Victor Shahnazi",
      "Loxysoft ID": 4922,
      "Datum": "2026-02-10",
      "År-månad": "2026-02",
      "Overksam tid": "0:00:00",
      "Overksam tid timmar": 0,
      "Väntetid": "0:00:00",
      "Väntetid timmar": 0,
      "Hanteringstid timmar": 0,
      "Inloggad tid": "8:00:00",
      "Inloggad tid timmar": 8,
      "Samtalstid": "0:00:00",
      "Samtalstid timmar": 0,
      "Efterbearbetstid": "0:00:00",
      "Efterbearbetstid timmar": 0,
      "Genomsnittlig samtalstid": "0:00:00",
      "Genomsnittlig samtalstid timmar": 0,
      "Genomsnittlig samtalstid/Order": "0:00:00",
      "Genomsnittlig samtalstid/Order timmar": 0,
      "Registrerade samtal": 0,
      "Registrerade prospekt": 0,
      "Avbrutit samtalsbegäran": 0,
      "Mansdagar": 1
    },
    "2026-02-11": {
      "Kund": "Global Connect",
      "Projekt": "Global Connect TM Jan",
      "Säljare": "Victor Shahnazi",
      "Loxysoft ID": 4922,
      "Datum": "2026-02-11",
      "År-månad": "2026-02",
      "Overksam tid": "0:00:00",
      "Overksam tid timmar": 0,
      "Väntetid": "0:00:00",
      "Väntetid timmar": 0,
      "Hanteringstid timmar": 0,
      "Inloggad tid": "8:00:00",
      "Inloggad tid timmar": 8,
      "Samtalstid": "0:00:00",
      "Samtalstid timmar": 0,
      "Efterbearbetstid": "0:00:00",
      "Efterbearbetstid timmar": 0,
      "Genomsnittlig samtalstid": "0:00:00",
      "Genomsnittlig samtalstid timmar": 0,
      "Genomsnittlig samtalstid/Order": "0:00:00",
      "Genomsnittlig samtalstid/Order timmar": 0,
      "Registrerade samtal": 0,
      "Registrerade prospekt": 0,
      "Avbrutit samtalsbegäran": 0,
      "Mansdagar": 1
    },
    "2026-02-12": {
      "Kund": "Global Connect",
      "Projekt": "Global Connect TM Jan",
      "Säljare": "Victor Shahnazi",
      "Loxysoft ID": 4922,
      "Datum": "2026-02-12",
      "År-månad": "2026-02",
      "Overksam tid": "0:00:00",
      "Overksam tid timmar": 0,
      "Väntetid": "0:00:00",
      "Väntetid timmar": 0,
      "Hanteringstid timmar": 0,
      "Inloggad tid": "8:00:00",
      "Inloggad tid timmar": 8,
      "Samtalstid": "0:00:00",
      "Samtalstid timmar": 0,
      "Efterbearbetstid": "0:00:00",
      "Efterbearbetstid timmar": 0,
      "Genomsnittlig samtalstid": "0:00:00",
      "Genomsnittlig samtalstid timmar": 0,
      "Genomsnittlig samtalstid/Order": "0:00:00",
      "Genomsnittlig samtalstid/Order timmar": 0,
      "Registrerade samtal": 0,
      "Registrerade prospekt": 0,
      "Avbrutit samtalsbegäran": 0,
      "Mansdagar": 1
    },
    "2026-02-13": {
      "Kund": "Telia",
      "Projekt": "Telia D2D",
      "Säljare": "Gabriel Burel",
      "Loxysoft ID": 6282,
      "Datum": "2026-02-13",
      "År-månad": "2026-02",
      "Overksam tid": "0:00:00",
      "Overksam tid timmar": 0,
      "Väntetid": "0:00:00",
      "Väntetid timmar": 0,
      "Hanteringstid timmar": 0,
      "Inloggad tid": "1:00:00",
      "Inloggad tid timmar": 1,
      "Samtalstid": "0:00:00",
      "Samtalstid timmar": 0,
      "Efterbearbetstid": "0:00:00",
      "Efterbearbetstid timmar": 0,
      "Genomsnittlig samtalstid": "0:00:00",
      "Genomsnittlig samtalstid timmar": 0,
      "Genomsnittlig samtalstid/Order": "0:00:00",
      "Genomsnittlig samtalstid/Order timmar": 0,
      "Registrerade samtal": 0,
      "Registrerade prospekt": 0,
      "Avbrutit samtalsbegäran": 0
    },
    "2026-02-14": {
      "Kund": "Telia",
      "Projekt": "Telia D2D",
      "Säljare": "Ali Fakih",
      "Loxysoft ID": 5833,
      "Datum": "2026-02-14",
      "År-månad": "2026-02",
      "Overksam tid": "0:00:00",
      "Overksam tid timmar": 0,
      "Väntetid": "0:00:00",
      "Väntetid timmar": 0,
      "Hanteringstid timmar": 0,
      "Inloggad tid": "1:00:00",
      "Inloggad tid timmar": 1,
      "Samtalstid": "0:00:00",
      "Samtalstid timmar": 0,
      "Efterbearbetstid": "0:00:00",
      "Efterbearbetstid timmar": 0,
      "Genomsnittlig samtalstid": "0:00:00",
      "Genomsnittlig samtalstid timmar": 0,
      "Genomsnittlig samtalstid/Order": "0:00:00",
      "Genomsnittlig samtalstid/Order timmar": 0,
      "Registrerade samtal": 0,
      "Registrerade prospekt": 0,
      "Avbrutit samtalsbegäran": 0
    },
    "2026-02-15": {
      "Kund": "Telia",
      "Projekt": "Telia D2D",
      "Säljare": "Max Nordenvärn",
      "Loxysoft ID": 6264,
      "Datum": "2026-02-15",
      "År-månad": "2026-02",
      "Overksam tid": "0:00:00",
      "Overksam tid timmar": 0,
      "Väntetid": "0:00:00",
      "Väntetid timmar": 0,
      "Hanteringstid timmar": 0,
      "Inloggad tid": "1:00:00",
      "Inloggad tid timmar": 1,
      "Samtalstid": "0:00:00",
      "Samtalstid timmar": 0,
      "Efterbearbetstid": "0:00:00",
      "Efterbearbetstid timmar": 0,
      "Genomsnittlig samtalstid": "0:00:00",
      "Genomsnittlig samtalstid timmar": 0,
      "Genomsnittlig samtalstid/Order": "0:00:00",
      "Genomsnittlig samtalstid/Order timmar": 0,
      "Registrerade samtal": 0,
      "Registrerade prospekt": 0,
      "Avbrutit samtalsbegäran": 0
    },
    "2026-02-16": {
      "Kund": "Global Connect",
      "Projekt": "Global Connect TM Jan",
      "Säljare": "Victor Shahnazi",
      "Loxysoft ID": 4922,
      "Datum": "2026-02-16",
      "År-månad": "2026-02",
      "Overksam tid": "0:00:00",
      "Overksam tid timmar": 0,
      "Väntetid": "0:00:00",
      "Väntetid timmar": 0,
      "Hanteringstid timmar": 0,
      "Inloggad tid": "8:00:00",
      "Inloggad tid timmar": 8,
      "Samtalstid": "0:00:00",
      "Samtalstid timmar": 0,
      "Efterbearbetstid": "0:00:00",
      "Efterbearbetstid timmar": 0,
      "Genomsnittlig samtalstid": "0:00:00",
      "Genomsnittlig samtalstid timmar": 0,
      "Genomsnittlig samtalstid/Order": "0:00:00",
      "Genomsnittlig samtalstid/Order timmar": 0,
      "Registrerade samtal": 0,
      "Registrerade prospekt": 0,
      "Avbrutit samtalsbegäran": 0,
      "Mansdagar": 1
    },
    "2026-02-17": {
      "Kund": "Telia",
      "Projekt": "Telia D2D",
      "Säljare": "Gabriel Burel",
      "Loxysoft ID": 6282,
      "Datum": "2026-02-17",
      "År-månad": "2026-02",
      "Overksam tid": "0:00:00",
      "Overksam tid timmar": 0,
      "Väntetid": "0:00:00",
      "Väntetid timmar": 0,
      "Hanteringstid timmar": 0,
      "Inloggad tid": "1:00:00",
      "Inloggad tid timmar": 1,
      "Samtalstid": "0:00:00",
      "Samtalstid timmar": 0,
      "Efterbearbetstid": "0:00:00",
      "Efterbearbetstid timmar": 0,
      "Genomsnittlig samtalstid": "0:00:00",
      "Genomsnittlig samtalstid timmar": 0,
      "Genomsnittlig samtalstid/Order": "0:00:00",
      "Genomsnittlig samtalstid/Order timmar": 0,
      "Registrerade samtal": 0,
      "Registrerade prospekt": 0,
      "Avbrutit samtalsbegäran": 0
    },
    "2026-02-18": {
      "Kund": "Global Connect",
      "Projekt": "Global Connect TM Jan",
      "Säljare": "Victor Shahnazi",
      "Loxysoft ID": 4922,
      "Datum": "2026-02-18",
      "År-månad": "2026-02",
      "Overksam tid": "0:00:00",
      "Overksam tid timmar": 0,
      "Väntetid": "0:00:00",
      "Väntetid timmar": 0,
      "Hanteringstid timmar": 0,
      "Inloggad tid": "8:00:00",
      "Inloggad tid timmar": 8,
      "Samtalstid": "0:00:00",
      "Samtalstid timmar": 0,
      "Efterbearbetstid": "0:00:00",
      "Efterbearbetstid timmar": 0,
      "Genomsnittlig samtalstid": "0:00:00",
      "Genomsnittlig samtalstid timmar": 0,
      "Genomsnittlig samtalstid/Order": "0:00:00",
      "Genomsnittlig samtalstid/Order timmar": 0,
      "Registrerade samtal": 0,
      "Registrerade prospekt": 0,
      "Avbrutit samtalsbegäran": 0,
      "Mansdagar": 1
    },
    "2026-02-19": {
      "Kund": "Telia",
      "Projekt": "Telia D2D",
      "Säljare": "Hassan Al-khafagi",
      "Loxysoft ID": 4564,
      "Datum": "2026-02-19",
      "År-månad": "2026-02",
      "Overksam tid": "0:00:00",
      "Overksam tid timmar": 0,
      "Väntetid": "0:00:00",
      "Väntetid timmar": 0,
      "Hanteringstid timmar": 0,
      "Inloggad tid": "1:00:00",
      "Inloggad tid timmar": 1,
      "Samtalstid": "0:00:00",
      "Samtalstid timmar": 0,
      "Efterbearbetstid": "0:00:00",
      "Efterbearbetstid timmar": 0,
      "Genomsnittlig samtalstid": "0:00:00",
      "Genomsnittlig samtalstid timmar": 0,
      "Genomsnittlig samtalstid/Order": "0:00:00",
      "Genomsnittlig samtalstid/Order timmar": 0,
      "Registrerade samtal": 0,
      "Registrerade prospekt": 0,
      "Avbrutit samtalsbegäran": 0
    },
    "2026-02-20": {
      "Kund": "Telia",
      "Projekt": "Telia D2D",
      "Säljare": "Toni Kara",
      "Loxysoft ID": 6539,
      "Datum": "2026-02-20",
      "År-månad": "2026-02",
      "Overksam tid": "0:00:00",
      "Overksam tid timmar": 0,
      "Väntetid": "0:00:00",
      "Väntetid timmar": 0,
      "Hanteringstid timmar": 0,
      "Inloggad tid": "1:00:00",
      "Inloggad tid timmar": 1,
      "Samtalstid": "0:00:00",
      "Samtalstid timmar": 0,
      "Efterbearbetstid": "0:00:00",
      "Efterbearbetstid timmar": 0,
      "Genomsnittlig samtalstid": "0:00:00",
      "Genomsnittlig samtalstid timmar": 0,
      "Genomsnittlig samtalstid/Order": "0:00:00",
      "Genomsnittlig samtalstid/Order timmar": 0,
      "Registrerade samtal": 0,
      "Registrerade prospekt": 0,
      "Avbrutit samtalsbegäran": 0
    },
    "2026-02-22": {
      "Kund": "Telia",
      "Projekt": "Telia D2D",
      "Säljare": "Ali Fakih",
      "Loxysoft ID": 5833,
      "Datum": "2026-02-22",
      "År-månad": "2026-02",
      "Overksam tid": "0:00:00",
      "Overksam tid timmar": 0,
      "Väntetid": "0:00:00",
      "Väntetid timmar": 0,
      "Hanteringstid timmar": 0,
      "Inloggad tid": "1:00:00",
      "Inloggad tid timmar": 1,
      "Samtalstid": "0:00:00",
      "Samtalstid timmar": 0,
      "Efterbearbetstid": "0:00:00",
      "Efterbearbetstid timmar": 0,
      "Genomsnittlig samtalstid": "0:00:00",
      "Genomsnittlig samtalstid timmar": 0,
      "Genomsnittlig samtalstid/Order": "0:00:00",
      "Genomsnittlig samtalstid/Order timmar": 0,
      "Registrerade samtal": 0,
      "Registrerade prospekt": 0,
      "Avbrutit samtalsbegäran": 0
    },
    "2026-02-21": {
      "Kund": "Telia",
      "Projekt": "Telia D2D",
      "Säljare": "Ali Fakih",
      "Loxysoft ID": 5833,
      "Datum": "2026-02-21",
      "År-månad": "2026-02",
      "Overksam tid": "0:00:00",
      "Overksam tid timmar": 0,
      "Väntetid": "0:00:00",
      "Väntetid timmar": 0,
      "Hanteringstid timmar": 0,
      "Inloggad tid": "9:00:00",
      "Inloggad tid timmar": 9,
      "Samtalstid": "0:00:00",
      "Samtalstid timmar": 0,
      "Efterbearbetstid": "0:00:00",
      "Efterbearbetstid timmar": 0,
      "Genomsnittlig samtalstid": "0:00:00",
      "Genomsnittlig samtalstid timmar": 0,
      "Genomsnittlig samtalstid/Order": "0:00:00",
      "Genomsnittlig samtalstid/Order timmar": 0,
      "Registrerade samtal": 0,
      "Registrerade prospekt": 0,
      "Avbrutit samtalsbegäran": 0,
      "Mansdagar": 1
    },
    "2026-02-23": {
      "Kund": "Global Connect",
      "Projekt": "Global Connect TM Jan",
      "Säljare": "Victor Shahnazi",
      "Loxysoft ID": 4922,
      "Datum": "2026-02-23",
      "År-månad": "2026-02",
      "Overksam tid": "0:00:00",
      "Overksam tid timmar": 0,
      "Väntetid": "0:00:00",
      "Väntetid timmar": 0,
      "Hanteringstid timmar": 0,
      "Inloggad tid": "8:00:00",
      "Inloggad tid timmar": 8,
      "Samtalstid": "0:00:00",
      "Samtalstid timmar": 0,
      "Efterbearbetstid": "0:00:00",
      "Efterbearbetstid timmar": 0,
      "Genomsnittlig samtalstid": "0:00:00",
      "Genomsnittlig samtalstid timmar": 0,
      "Genomsnittlig samtalstid/Order": "0:00:00",
      "Genomsnittlig samtalstid/Order timmar": 0,
      "Registrerade samtal": 0,
      "Registrerade prospekt": 0,
      "Avbrutit samtalsbegäran": 0,
      "Mansdagar": 1
    }
  }
}